pysesd/__init__.py
pysesd/sesd.py
pysesd/util.py
pysesd-0.1.0.dist-info/METADATA
pysesd-0.1.0.dist-info/WHEEL
pysesd-0.1.0.dist-info/licenses/LICENSE
pysesd-0.1.0.dist-info/RECORD
