Metadata-Version: 2.1
Name: pysesd
Version: 0.1.0
Summary: Add a short description here
Author-email: Xiangzhuang Shen <datahonor@gmail.com>
License-File: LICENSE
Requires-Python: >=3.8
Requires-Dist: matplotlib~=3.7.1
Requires-Dist: numpy~=1.24.3
Requires-Dist: pandas~=2.0.2
Requires-Dist: scipy~=1.10.1
Requires-Dist: statsmodels~=0.14.0
